[
    {
        "start": "00:00:00,000",
        "end": "00:00:04,940",
        "lang": "zh",
        "text": "来品鉴一下今天的胡萝卜拌牛肉"
    },
    {
        "start": "00:00:09,059",
        "end": "00:00:10,000",
        "lang": "zh",
        "text": "尝一下牛肉"
    },
    {
        "start": "00:00:11,140",
        "end": "00:00:12,240",
        "lang": "zh",
        "text": "胡萝卜很好吃"
    },
    {
        "start": "00:00:13,520",
        "end": "00:00:14,520",
        "lang": "zh",
        "text": "真的是超级好吃"
    },
    {
        "start": "00:00:17,580",
        "end": "00:00:18,520",
        "lang": "zh",
        "text": "酸辣失忆"
    },
    {
        "start": "00:00:20,214",
        "end": "00:00:25,814",
        "lang": "en",
        "text": " Top notch. I think this is top notch. I'm a top chef."
    },
    {
        "start": "00:00:29,890",
        "end": "00:00:31,510",
        "lang": "zh",
        "text": "簡直就是中西結合的典範"
    },
    {
        "start": "00:00:33,026",
        "end": "00:00:44,546",
        "lang": "en",
        "text": " I think this is a classic example as a combination of eastern and western cooking."
    },
    {
        "start": "00:00:47,458",
        "end": "00:00:47,818",
        "lang": "ja",
        "text": "好きよ"
    },
    {
        "start": "00:00:52,866",
        "end": "00:00:53,046",
        "lang": "en",
        "text": " Okay."
    },
    {
        "start": "00:00:53,698",
        "end": "00:00:53,798",
        "lang": "en",
        "text": " impres"
    }
]